stochastic_pseudonymizer/__init__.py
stochastic_pseudonymizer/stochastic_pseudonymizer.py
stochastic_pseudonymizer-1.0.0.dist-info/METADATA
stochastic_pseudonymizer-1.0.0.dist-info/WHEEL
stochastic_pseudonymizer-1.0.0.dist-info/licenses/LICENSE
stochastic_pseudonymizer-1.0.0.dist-info/RECORD
