Metadata-Version: 2.4
Name: stochastic-pseudonymizer
Version: 1.0.0
Summary: Generate pseudonymous tokens with built-in plausible deniability
Project-URL: Homepage, https://github.com/chimpy-me/stochastic-pseudonymizer
Project-URL: Repository, https://github.com/chimpy-me/stochastic-pseudonymizer
Author-email: Ray Voelker <ray.voelker@gmail.com>
License-Expression: MIT
License-File: LICENSE
Requires-Python: >=3.9
